notifier/__init__.py
notifier/notifier.py
repo_notifier-0.1.2.dist-info/METADATA
repo_notifier-0.1.2.dist-info/WHEEL
repo_notifier-0.1.2.dist-info/entry_points.txt
repo_notifier-0.1.2.dist-info/top_level.txt
repo_notifier-0.1.2.dist-info/RECORD
