Metadata-Version: 2.4
Name: repo-notifier
Version: 0.1.2
Summary: A CLI tool that emails a friend when you create a new GitHub repo
Home-page: https://github.com/Priyanshu-1477/repo-notifier
Author: Priyanshu Raj
Author-email: your_email@example.com
Classifier: Programming Language :: Python :: 3
Classifier: License :: OSI Approved :: MIT License
Classifier: Operating System :: OS Independent
Requires-Python: >=3.6
Requires-Dist: requests
Requires-Dist: python-dotenv
Requires-Dist: rich
Dynamic: author
Dynamic: author-email
Dynamic: classifier
Dynamic: description
Dynamic: description-content-type
Dynamic: home-page
Dynamic: requires-dist
Dynamic: requires-python
Dynamic: summary
